mlstatpy/__init__.py
mlstatpy/ext_test_case.py
mlstatpy/render_js_dot.py
mlstatpy/data/__init__.py
mlstatpy/data/data_exceptions.py
mlstatpy/data/wikipedia.py
mlstatpy/garden/__init__.py
mlstatpy/garden/poulet.py
mlstatpy/graph/__init__.py
mlstatpy/graph/graph_distance.py
mlstatpy/image/__init__.py
mlstatpy/image/detection_segment/__init__.py
mlstatpy/image/detection_segment/detection_nfa.py
mlstatpy/image/detection_segment/detection_segment.py
mlstatpy/image/detection_segment/detection_segment_bord.py
mlstatpy/image/detection_segment/detection_segment_segangle.py
mlstatpy/image/detection_segment/geometrie.py
mlstatpy/image/detection_segment/queue_binom.py
mlstatpy/image/detection_segment/random_image.py
mlstatpy/ml/__init__.py
mlstatpy/ml/_neural_tree_api.py
mlstatpy/ml/_neural_tree_node.py
mlstatpy/ml/kppv.py
mlstatpy/ml/kppv_laesa.py
mlstatpy/ml/logreg.py
mlstatpy/ml/matrices.py
mlstatpy/ml/neural_tree.py
mlstatpy/ml/roc.py
mlstatpy/ml/voronoi.py
mlstatpy/nlp/__init__.py
mlstatpy/nlp/completion.py
mlstatpy/nlp/completion_simple.py
mlstatpy/nlp/normalize.py
mlstatpy/optim/__init__.py
mlstatpy/optim/sgd.py
mlstatpy-0.4.0.dist-info/LICENSE.txt
mlstatpy-0.4.0.dist-info/METADATA
mlstatpy-0.4.0.dist-info/WHEEL
mlstatpy-0.4.0.dist-info/top_level.txt
mlstatpy-0.4.0.dist-info/RECORD
