Metadata-Version: 2.1
Name: mlstatpy
Version: 0.4.0
Summary: Points de détails liés au machine learning
Home-page: https://github.com/sdpython/mlstatpy
Author: Xavier Dupré
Author-email: xavier.dupre@gmail.com
Classifier: Intended Audience :: Science/Research
Classifier: Intended Audience :: Education
Classifier: License :: OSI Approved :: MIT License
Classifier: Programming Language :: Python
Classifier: Topic :: Scientific/Engineering
Classifier: Topic :: Scientific/Engineering :: Mathematics
Classifier: Topic :: Education
Classifier: Development Status :: 5 - Production/Stable
Classifier: Operating System :: OS Independent
Classifier: Programming Language :: Python :: 3
Classifier: Programming Language :: Python :: 3.9
Classifier: Programming Language :: Python :: 3.10
Classifier: Programming Language :: Python :: 3.11
License-File: LICENSE.txt
Requires-Dist: mlinsights>=0.2
Requires-Dist: onnxruntime>=1.12
Requires-Dist: skl2onnx
